CHANGES.rst
CONTRIBUTORS.rst
MANIFEST.in
Makefile
README.rst
buildout.cfg
setup.py
travis.cfg
buildout.d/base.cfg
buildout.d/checkouts.cfg
buildout.d/development.cfg
buildout.d/jenkins.cfg
buildout.d/sources.cfg
buildout.d/versions.cfg
docs/LICENSE.GPL
docs/LICENSE.rst
src/collective/__init__.py
src/collective.delaycalculator.egg-info/PKG-INFO
src/collective.delaycalculator.egg-info/SOURCES.txt
src/collective.delaycalculator.egg-info/dependency_links.txt
src/collective.delaycalculator.egg-info/entry_points.txt
src/collective.delaycalculator.egg-info/namespace_packages.txt
src/collective.delaycalculator.egg-info/not-zip-safe
src/collective.delaycalculator.egg-info/requires.txt
src/collective.delaycalculator.egg-info/top_level.txt
src/collective/delaycalculator/__init__.py
src/collective/delaycalculator/configure.zcml
src/collective/delaycalculator/interfaces.py
src/collective/delaycalculator/setuphandlers.py
src/collective/delaycalculator/testing.py
src/collective/delaycalculator/testing.zcml
src/collective/delaycalculator/browser/__init__.py
src/collective/delaycalculator/browser/configure.zcml
src/collective/delaycalculator/browser/static/.gitkeep
src/collective/delaycalculator/content/__init__.py
src/collective/delaycalculator/content/configure.zcml
src/collective/delaycalculator/locales/collective.delaycalculator.pot
src/collective/delaycalculator/locales/update.sh
src/collective/delaycalculator/locales/fr/LC_MESSAGES/collective.delaycalculator.po
src/collective/delaycalculator/profiles/default/browserlayer.xml
src/collective/delaycalculator/profiles/default/collectivedelaycalculator_marker.txt
src/collective/delaycalculator/profiles/default/metadata.xml
src/collective/delaycalculator/profiles/testing/metadata.xml
src/collective/delaycalculator/tests/__init__.py
src/collective/delaycalculator/tests/test_robot.py
src/collective/delaycalculator/tests/test_setup.py
src/collective/delaycalculator/tests/robot/.gitkeep