Metadata-Version: 1.1
Name: collective.delaycalculator
Version: 0.1
Summary: calcul a delay between two dates and a date after a delay
Home-page: http://pypi.python.org/pypi/collective.delaycalculator
Author: Franck NGAHA
Author-email: franck.ngaha@imio.be
License: GPL V2
Keywords: Python Zope Plone
Platform: UNKNOWN
Classifier: Environment :: Web Environment
Classifier: Framework :: Plone
Classifier: Framework :: Plone :: 4.3
Classifier: Programming Language :: Python
Classifier: Programming Language :: Python :: 2.7
